Workbook

Sheet Guide
A1: Assignment 1 | Model guide and scope
A4: Purpose: compare a hypothetical 200-user SME’s Exchange SE and Google Workspace options over 2026–2030, while separating supplier CAC/LTV from buyer TCO.
A7: All numeric commercial, cost, risk and churn inputs are ILLUSTRATIVE ASSUMPTIONS supplied or explicitly derived from the case. No vendor customer cohort or empirical fit is represented.
A10: Blue cells on Inputs are editable; other sheets use Excel formulas. Changing baseline n updates B1 through the Churn sheet. Charts on Charts update with their linked data.
A13: LTV timing: an account active at the start of a year earns that year’s contribution; churn occurs at year-end. Cash is discounted at year-end. Thus survival exponent is t−1, not t.
A16: Risk loss is a 5% haircut to contribution, not a second churn probability. Annual churn is independent and held constant within each scenario; no terminal value is used.
A19: Cross-subsidy is a hypothetical USD 30,000 credit against USD 70,000 gross acquisition spending. Net allocated CAC falls, but ecosystem-wide resource cost remains USD 7,000/account. No actual Google transfer is claimed.
A22: TCO: nominal USD cash costs, opening-2026 one-off payments, five annual recurring payments. 200 seats, fixed prices, no tax/inflation/discount, zero residual value. Common connectivity and endpoints are excluded equally.
A25: Sensitivity varies only Google subscription price and Exchange FTE at USD 80,000/FTE/year. A USD 14 plan is a cost stress, not an assertion of equal plan features.
A28: Sources maps the official documentation to specific claims and records publication/revision dates. Licensing, staffing and hardware inputs are planning assumptions; procurement requires current entitlements and comparable quotations.
A31: Readiness: see Checks. Cached values are included; open in Excel/LibreOffice to recalculate after changing inputs. External PNG/PDF/SVG figures represent the original baseline and do not auto-refresh.
A34: Submission: student must review all reasoning and citations, add identification as required, complete VeriGuide and the institution’s Signed Declaration, attach authentic evidence and submit via Blackboard.

Sheet Inputs
A1: Inputs | All numbers are illustrative assumptions
A3: Parameter | B3: Value | C3: Units | D3: Definition / boundary
A4: employees | B4: 200 | C4: users | D4: Constant licensed users, 2026-2030.
A5: years | B5: 5 | C5: years | D5: Finite operational horizon; no terminal value.
A6: first_year | B6: 2026 | C6: year | D6: Cash costs start at opening of 2026.
A7: clients | B7: 10 | C7: enterprise accounts | D7: Each supplier acquires this many accounts.
A8: exchange_acq | B8: 70000 | C8: USD | D8: Illustrative gross/net acquisition budget.
A9: google_gross_acq | B9: 70000 | C9: USD | D9: Hypothetical common gross campaign cost.
A10: ecosystem_credit | B10: 30000 | C10: USD | D10: Illustrative adjacent-business funding; allocation only.
A11: annual_gp | B11: 6000 | C11: USD/account/year | D11: Standardized contribution before operating-risk haircut.
A12: risk_loss | B12: 0.05 | C12: fraction/year | D12: Expected contribution loss, distinct from churn.
A13: discount | B13: 0.1 | C13: fraction/year | D13: Annual end-of-year discount rate.
A14: churn_base | B14: 0.18 | C14: fraction/year | D14: Illustrative churn at n=0; not fitted to data.
A15: churn_beta | B15: 0.1 | C15: per integration | D15: Illustrative exponential decay coefficient.
... A28: low_fte | B28: 0.15 | C28: FTE | D28: Lower on-premises staffing sensitivity scenario.

Sheet CAC_LTV
A1: B1 | Supplier-level CAC and risk-adjusted LTV
A3: Metric | B3: Exchange SE | C3: Google Workspace
A4: Gross acquisition spending | B4: =Inputs!$B$8 -> 70000 | C4: =Inputs!$B$9 -> 70000
A5: Ecosystem funding credit | B5: =0 -> 0 | C5: =Inputs!$B$10 -> 30000
A6: Net allocated acquisition cost | B6: =B4-B5 -> 70000 | C6: =C4-C5 -> 40000
A7: CAC per acquired account | B7: =B6/Inputs!$B$7 -> 7000 | C7: =C6/Inputs!$B$7 -> 4000
A8: 5-year risk-adjusted LTV | B8: =SUM(G18:G22) -> 17398.867 | C8: =SUM(G18:G22) -> 17398.867
A9: LTV / net allocated CAC | B9: =B8/B7 -> 2.4855524 | C9: =C8/C7 -> 4.3497167
A10: Gross resource CAC (no funding credit) | B10: =B4/Inputs!$B$7 -> 7000 | C10: =C4/Inputs!$B$7 -> 7000
A11: LTV / gross resource CAC | B11: =B8/B10 -> 2.4855524 | C11: =C8/C10 -> 2.4855524
A13: Selected baseline n | B13: =Inputs!$B$16 -> 4
A14: Linked baseline annual churn | B14: =INDEX(Churn!B4:B8,MATCH(B13,Churn!A4:A8,0)) -> 0.12065761
A17: Year t | B17: Calendar year | C17: Start-year survival | D17: End-year retention | E17: Risk-adjusted GP | F17: Discount factor | G17: Present value
A18: 1 | B18: =Inputs!$B$6+A18-1 -> 2026 | C18: =(1-$B$14)^(A18-1) -> 1 | D18: =(1-$B$14)^A18 -> 0.87934239 | E18: =Inputs!$B$11*(1-Inputs!$B$12)*C18 -> 5700 | F18: =1/(1+Inputs!$B$13)^A18 -> 0.90909091 | G18: =E18*F18 -> 5181.8182
A19: 2 | B19: =Inputs!$B$6+A19-1 -> 2027 | C19: =(1-$B$14)^(A19-1) -> 0.87934239 | D19: =(1-$B$14)^A19 -> 0.77324304 | E19: =Inputs!$B$11*(1-Inputs!$B$12)*C19 -> 5012.2516 | F19: =1/(1+Inputs!$B$13)^A19 -> 0.82644628 | G19: =E19*F19 -> 4142.3567
A20: 3 | B20: =Inputs!$B$6+A20-1 -> 2028 | C20: =(1-$B$14)^(A20-1) -> 0.77324304 | D20: =(1-$B$14)^A20 -> 0.67994539 | E20: =Inputs!$B$11*(1-Inputs!$B$12)*C20 -> 4407.4853 | F20: =1/(1+Inputs!$B$13)^A20 -> 0.7513148 | G20: =E20*F20 -> 3311.409
A21: 4 | B21: =Inputs!$B$6+A21-1 -> 2029 | C21: =(1-$B$14)^(A21-1) -> 0.67994539 | D21: =(1-$B$14)^A21 -> 0.5979048 | E21: =Inputs!$B$11*(1-Inputs!$B$12)*C21 -> 3875.6887 | F21: =1/(1+Inputs!$B$13)^A21 -> 0.68301346 | G21: =E21*F21 -> 2647.1475
A22: 5 | B22: =Inputs!$B$6+A22-1 -> 2030 | C22: =(1-$B$14)^(A22-1) -> 0.5979048 | D22: =(1-$B$14)^A22 -> 0.52576304 | E22: =Inputs!$B$11*(1-Inputs!$B$12)*C22 -> 3408.0574 | F22: =1/(1+Inputs!$B$13)^A22 -> 0.62092132 | G22: =E22*F22 -> 2116.1355
A24: Alternative timing LTV | B24: =B8*(1-B14) -> 15299.561
A27: The report presents the formal LTV equation. This sheet sums five discounted annual contributions, weighted by start-year survival. Alternative timing requires survival through year 1; neither convention includes a terminal value.
A30: Funding credit changes the cost assigned to the focal product, not total ecosystem resource use. This is a transparent hypothetical cross-subsidy mechanism, not observed Google or Microsoft financial performance.

Sheet Churn
A1: B2 | Integration scenarios and retained customers
A3: n (count) | B3: Annual churn | C3: End-2030 retention | D3: 5-year LTV (USD) | E3: Exchange LTV/CAC | F3: Google LTV/CAC
A4: 0 | B4: =Inputs!$B$14*EXP(-Inputs!$B$15*A4) -> 0.18 | C4: =(1-B4)^Inputs!$B$5 -> 0.37073984 | D4: =Inputs!$B$11*(1-Inputs!$B$12)*(1-B4)^0/(1+Inputs!$B$13)^1+Inputs!$B$11*(1-Inputs!$B$12)*(1-B4)^1/(1+Inputs!$B$13)^2+Inputs!$B$11*(1-Inputs!$B$12)*(1-B4)^2/(1+Inputs!$B$13)^3+Inputs!$B$11*(1-Inputs!$B$12)*(1-B4)^3/(1+Inputs!$B$13)^4+Inputs!$B$11*(1-Inputs!$B$12)*(1-B4)^4/(1+Inputs!$B$13)^5 -> 15670.923 | E4: =D4/CAC_LTV!$B$7 -> 2.2387033 | F4: =D4/CAC_LTV!$C$7 -> 3.9177307
A5: 2 | B5: =Inputs!$B$14*EXP(-Inputs!$B$15*A5) -> 0.14737154 | C5: =(1-B5)^Inputs!$B$5 -> 0.45060825 | D5: =Inputs!$B$11*(1-Inputs!$B$12)*(1-B5)^0/(1+Inputs!$B$13)^1+Inputs!$B$11*(1-Inputs!$B$12)*(1-B5)^1/(1+Inputs!$B$13)^2+Inputs!$B$11*(1-Inputs!$B$12)*(1-B5)^2/(1+Inputs!$B$13)^3+Inputs!$B$11*(1-Inputs!$B$12)*(1-B5)^3/(1+Inputs!$B$13)^4+Inputs!$B$11*(1-Inputs!$B$12)*(1-B5)^4/(1+Inputs!$B$13)^5 -> 16595.216 | E5: =D5/CAC_LTV!$B$7 -> 2.3707451 | F5: =D5/CAC_LTV!$C$7 -> 4.148804
A6: 4 | B6: =Inputs!$B$14*EXP(-Inputs!$B$15*A6) -> 0.12065761 | C6: =(1-B6)^Inputs!$B$5 -> 0.52576304 | D6: =Inputs!$B$11*(1-Inputs!$B$12)*(1-B6)^0/(1+Inputs!$B$13)^1+Inputs!$B$11*(1-Inputs!$B$12)*(1-B6)^1/(1+Inputs!$B$13)^2+Inputs!$B$11*(1-Inputs!$B$12)*(1-B6)^2/(1+Inputs!$B$13)^3+Inputs!$B$11*(1-Inputs!$B$12)*(1-B6)^3/(1+Inputs!$B$13)^4+Inputs!$B$11*(1-Inputs!$B$12)*(1-B6)^4/(1+Inputs!$B$13)^5 -> 17398.867 | E6: =D6/CAC_LTV!$B$7 -> 2.4855524 | F6: =D6/CAC_LTV!$C$7 -> 4.3497167
A7: 6 | B7: =Inputs!$B$14*EXP(-Inputs!$B$15*A7) -> 0.098786094 | C7: =(1-B7)^Inputs!$B$5 -> 0.59448297 | D7: =Inputs!$B$11*(1-Inputs!$B$12)*(1-B7)^0/(1+Inputs!$B$13)^1+Inputs!$B$11*(1-Inputs!$B$12)*(1-B7)^1/(1+Inputs!$B$13)^2+Inputs!$B$11*(1-Inputs!$B$12)*(1-B7)^2/(1+Inputs!$B$13)^3+Inputs!$B$11*(1-Inputs!$B$12)*(1-B7)^3/(1+Inputs!$B$13)^4+Inputs!$B$11*(1-Inputs!$B$12)*(1-B7)^4/(1+Inputs!$B$13)^5 -> 18089.672 | E7: =D7/CAC_LTV!$B$7 -> 2.5842388 | F7: =D7/CAC_LTV!$C$7 -> 4.522418
A8: 8 | B8: =Inputs!$B$14*EXP(-Inputs!$B$15*A8) -> 0.080879214 | C8: =(1-B8)^Inputs!$B$5 -> 0.65593822 | D8: =Inputs!$B$11*(1-Inputs!$B$12)*(1-B8)^0/(1+Inputs!$B$13)^1+Inputs!$B$11*(1-Inputs!$B$12)*(1-B8)^1/(1+Inputs!$B$13)^2+Inputs!$B$11*(1-Inputs!$B$12)*(1-B8)^2/(1+Inputs!$B$13)^3+Inputs!$B$11*(1-Inputs!$B$12)*(1-B8)^3/(1+Inputs!$B$13)^4+Inputs!$B$11*(1-Inputs!$B$12)*(1-B8)^4/(1+Inputs!$B$13)^5 -> 18678.042 | E8: =D8/CAC_LTV!$B$7 -> 2.6682918 | F8: =D8/CAC_LTV!$C$7 -> 4.6695106
A11: Scenarios are alternative integration counts, not successive calendar years. Within each scenario, churn and n remain constant through 2026–2030. Retention=(1−c)^5, conditional on presence at opening-2026.
A14: No causal estimate is claimed. Data quality, usability, customer mix and portability could change the sign or magnitude of an observed relationship. API availability alone does not prove retention.

Sheet TCO
A1: B3 | Buyer-level nominal cash costs, 2026–2030
A3: Cash cost category | B3: Exchange SE (USD) | C3: Google (USD) | D3: Timing / scope
A4: Hardware / storage | B4: =Inputs!$B$17 -> 32000 | C4: =0 -> 0 | D4: Opening-2026; zero residual value
A5: Deployment / migration | B5: =Inputs!$B$18 -> 9000 | C5: =Inputs!$B$24 -> 15000 | D5: Opening-2026; cloud includes training
A6: Total one-off | B6: =SUM(B4:B5) -> 41000 | C6: =SUM(C4:C5) -> 15000 | D6: Do not add again to recurring expenses
A7: Licensing / subscriptions | B7: =Inputs!$B$19 -> 12000 | C7: =Inputs!$B$4*Inputs!$B$25*12 -> 16800 | D7: Annual; illustrative licensing allowance / price
A8: Administration | B8: =Inputs!$B$20*Inputs!$B$21 -> 24000 | C8: =Inputs!$B$26 -> 8000 | D8: Annual; USD 80,000/FTE/year for Exchange
A9: Facilities/network/maintenance | B9: =Inputs!$B$22 -> 7000 | C9: =0 -> 0 | D9: Annual incremental on-premises allowance
A10: Backup / added security | B10: =Inputs!$B$23 -> 5000 | C10: =Inputs!$B$23 -> 5000 | D10: Annual incremental control allowance
A11: Total annual recurring | B11: =SUM(B7:B10) -> 48000 | C11: =SUM(C7:C10) -> 29800 | D11: Five recurring payments
A12: Five-year TCO | B12: =B6+Inputs!$B$5*B11 -> 281000 | C12: =C6+Inputs!$B$5*C11 -> 164000 | D12: Nominal USD; no discounting
A14: Google savings (USD) | B14: =B12-C12 -> 117000
A15: Savings / Exchange TCO | B15: =B14/B12 -> 0.41637011
A18: Cash year | B18: Exchange SE | C18: Google Workspace | D18: Cumulative Exchange | E18: Cumulative Google
A19: 2026 | B19: =$B$11+$B$6 -> 89000 | C19: =$C$11+$C$6 -> 44800 | D19: =SUM(B19:B19) -> 89000 | E19: =SUM(C19:C19) -> 44800
A20: 2027 | B20: =$B$11 -> 48000 | C20: =$C$11 -> 29800 | D20: =SUM(B19:B20) -> 137000 | E20: =SUM(C19:C20) -> 74600
A21: 2028 | B21: =$B$11 -> 48000 | C21: =$C$11 -> 29800 | D21: =SUM(B19:B21) -> 185000 | E21: =SUM(C19:C21) -> 104400
A22: 2029 | B22: =$B$11 -> 48000 | C22: =$C$11 -> 29800 | D22: =SUM(B19:B22) -> 233000 | E22: =SUM(C19:C22) -> 134200
A23: 2030 | B23: =$B$11 -> 48000 | C23: =$C$11 -> 29800 | D23: =SUM(B19:B23) -> 281000 | E23: =SUM(C19:C23) -> 164000
A26: The two-server allowance is a cost scenario, not a validated resilient architecture. Existing directory/DNS capacity is assumed reusable. Required OS/CAL/SE entitlements and backup design must be checked with current official terms and a reseller quote.
A29: Excluded symmetrically: common endpoints/internet, tax, inflation, financing, productivity valuation and outage losses. No hardware refresh or decommissioning cost is modeled; prices and users stay constant. Feature equivalence and regulatory suitability are not established.

Sheet Sensitivity
A1: Sensitivity | Two-variable cost reversal test
A3: Google USD/user/month | B3: Exchange FTE | C3: Exchange TCO | D3: Google TCO | E3: Google savings | F3: Preferred by cost
A4: =Inputs!$B$25 -> 7 | B4: =Inputs!$B$21 -> 0.3 | C4: =Inputs!$B$17+Inputs!$B$18+Inputs!$B$5*(Inputs!$B$19+Inputs!$B$20*B4+Inputs!$B$22+Inputs!$B$23) -> 281000 | D4: =Inputs!$B$24+Inputs!$B$5*(Inputs!$B$4*A4*12+Inputs!$B$26+Inputs!$B$23) -> 164000 | E4: =C4-D4 -> 117000 | F4: =IF(E4>0,"Google",IF(E4<0,"Exchange","Tie")) -> Google
A5: =Inputs!$B$25 -> 7 | B5: =Inputs!$B$28 -> 0.15 | C5: =Inputs!$B$17+Inputs!$B$18+Inputs!$B$5*(Inputs!$B$19+Inputs!$B$20*B5+Inputs!$B$22+Inputs!$B$23) -> 221000 | D5: =Inputs!$B$24+Inputs!$B$5*(Inputs!$B$4*A5*12+Inputs!$B$26+Inputs!$B$23) -> 164000 | E5: =C5-D5 -> 57000 | F5: =IF(E5>0,"Google",IF(E5<0,"Exchange","Tie")) -> Google
A6: =Inputs!$B$27 -> 14 | B6: =Inputs!$B$21 -> 0.3 | C6: =Inputs!$B$17+Inputs!$B$18+Inputs!$B$5*(Inputs!$B$19+Inputs!$B$20*B6+Inputs!$B$22+Inputs!$B$23) -> 281000 | D6: =Inputs!$B$24+Inputs!$B$5*(Inputs!$B$4*A6*12+Inputs!$B$26+Inputs!$B$23) -> 248000 | E6: =C6-D6 -> 33000 | F6: =IF(E6>0,"Google",IF(E6<0,"Exchange","Tie")) -> Google
A7: =Inputs!$B$27 -> 14 | B7: =Inputs!$B$28 -> 0.15 | C7: =Inputs!$B$17+Inputs!$B$18+Inputs!$B$5*(Inputs!$B$19+Inputs!$B$20*B7+Inputs!$B$22+Inputs!$B$23) -> 221000 | D7: =Inputs!$B$24+Inputs!$B$5*(Inputs!$B$4*A7*12+Inputs!$B$26+Inputs!$B$23) -> 248000 | E7: =C7-D7 -> -27000 | F7: =IF(E7>0,"Google",IF(E7<0,"Exchange","Tie")) -> Exchange
A10: Exchange FTE | B10: Break-even Google price | C10: Units
A11: =Inputs!$B$21 -> 0.3 | B11: =(Inputs!$B$17+Inputs!$B$18+Inputs!$B$5*(Inputs!$B$19+Inputs!$B$20*A11+Inputs!$B$22+Inputs!$B$23)-Inputs!$B$24-Inputs!$B$5*(Inputs!$B$26+Inputs!$B$23))/(Inputs!$B$5*Inputs!$B$4*12) -> 16.75 | C11: USD/user/month
A12: =Inputs!$B$28 -> 0.15 | B12: =(Inputs!$B$17+Inputs!$B$18+Inputs!$B$5*(Inputs!$B$19+Inputs!$B$20*A12+Inputs!$B$22+Inputs!$B$23)-Inputs!$B$24-Inputs!$B$5*(Inputs!$B$26+Inputs!$B$23))/(Inputs!$B$5*Inputs!$B$4*12) -> 11.75 | C12: USD/user/month
A15: Positive savings favour Google. At USD 14/user/month and 0.15 Exchange FTE, Exchange is USD 27,000 cheaper. This does not prove either plan meets the same functional or compliance requirements.

Sheet Charts
A1: Figures | Linked Excel charts
A49: Baseline TCO: USD 7/user/month and 0.30 Exchange FTE. The line chart uses integration scenarios, not calendar time. External figure files are static exports of the initial baseline.

Sheet Sources
A1: Official sources | Claim mapping and access audit
A3: ID | B3: Organization / date | C3: Title | D3: Official URL | E3: Supported use | F3: Verification status | G3: Official GitHub source | H3: Citation date basis
A4: G1 | B4: Google (2006) | C4: Get your people talking | D4: https://googleblog.blogspot.com/2006/08/get-your-people-talking.html | E4: Historical entry into hosted enterprise applications in 2006. | F4: VERIFIED: original official announcement retrieved; dated 28 August 2006. | H4: 2006-08-28 — Date displayed on the original announcement
A5: G2 | B5: Google (n.d.) | C5: Google Workspace pricing | D5: https://workspace.google.com/pricing.html | E5: Current suite scope and annual-commitment price context; flat five-year USD 7/14 inputs remain illustrative assumptions. | F5: VERIFIED: official pricing page retrieved. Annual-commitment standard USD 7/14 displayed, with separate promotions; five-year flat prices remain assumptions. | H5: Undated — No publication/revision date displayed
A6: G3 | B6: Google (2025) | C6: Google Workspace Marketplace | D6: https://developers.google.com/workspace/marketplace | E6: Third-party app distribution and integration ecosystem; no installed-base or network-effect estimate. | F6: VERIFIED: official Marketplace overview retrieved; third-party apps and add-on publishing documented. | H6: 2025-09-26 — Displayed last-updated date
A7: G4 | B7: Google (2026b) | C7: Gmail API: Python quickstart | D7: https://developers.google.com/workspace/gmail/api/quickstart/python | E7: OAuth scopes, credentials and Gmail label-list API in official sample. | F7: VERIFIED: official developer page and official GitHub source both retrieved. | G7: https://raw.githubusercontent.com/googleworkspace/python-samples/main/gmail/quickstart/quickstart.py | H7: 2026-10-12 — Displayed last-updated date
A8: G5 | B8: Google (2026a) | C8: Admin SDK Directory API: Python quickstart | D8: https://developers.google.com/workspace/admin/directory/v1/quickstart/python | E8: Directory user-list API, OAuth scope and credential dependency. | F8: VERIFIED: official developer page and official GitHub source both retrieved. | G8: https://raw.githubusercontent.com/googleworkspace/python-samples/main/admin_sdk/directory/quickstart.py | H8: 2026-10-12 — Displayed last-updated date
A9: G6 | B9: Google (2026c) | C9: Google Drive API: Python quickstart | D9: https://developers.google.com/workspace/drive/api/quickstart/python | E9: Drive file metadata access through a scoped API; not proof of full-fidelity migration. | F9: VERIFIED: official developer page and official GitHub source both retrieved. | G9: https://raw.githubusercontent.com/googleworkspace/python-samples/main/drive/quickstart/quickstart.py | H9: 2026-10-12 — Displayed last-updated date
A10: M2 | B10: Microsoft (2026a) | C10: New-Mailbox (ExchangePowerShell) | D10: https://learn.microsoft.com/powershell/module/exchangepowershell/new-mailbox | E10: Official applicability lists both Exchange Server SE and Exchange Online; mailbox and user-account creation. | F10: Official Microsoft Learn page and MicrosoftDocs source reviewed. | G10: https://raw.githubusercontent.com/MicrosoftDocs/office-docs-powershell/main/exchange/exchange-ps/ExchangePowerShell/New-Mailbox.md | H10: 2026-05-16 — Revision date in official page updated_at metadata
A11: M3 | B11: Microsoft (2026b) | C11: New-MigrationBatch (ExchangePowerShell) | D11: https://learn.microsoft.com/powershell/module/exchangepowershell/new-migrationbatch | E11: Batched migration requests, endpoints and environment-specific parameters. | F11: Official Microsoft Learn page and MicrosoftDocs source reviewed. | G11: https://raw.githubusercontent.com/MicrosoftDocs/office-docs-powershell/main/exchange/exchange-ps/ExchangePowerShell/New-MigrationBatch.md | H11: 2026-05-28 — Revision date in official page updated_at metadata
A12: M4 | B12: Microsoft (2025a) | C12: Exchange Online service description | D12: https://learn.microsoft.com/en-us/office365/servicedescriptions/exchange-online-service-description/exchange-online-service-description | E12: Exchange Online as the procurement comparator; current price/features not asserted. | F12: Official Microsoft Learn service description reviewed; Exchange Online price is outside the quantified scenario. | H12: 2025-12-09 — Displayed last-updated date
A13: M5 | B13: Microsoft (2025b) | C13: Exchange Server architecture | D13: https://learn.microsoft.com/en-us/exchange/architecture/architecture?view=exchserver-2019 | E13: Exchange Mailbox server architecture and administration; the page applies to Subscription Edition. | F13: VERIFIED: official Learn architecture page retrieved; current page applies to Subscription Edition. | H13: 2025-04-02 — Displayed last-updated date
A14: M6 | B14: Microsoft (2025c) | C14: What is new in Exchange Server Subscription Edition (SE) | D14: https://learn.microsoft.com/en-us/exchange/new-features/new-features?view=exchserver-2019 | E14: Current Exchange Server/SE product context; no retirement or release-date assertion is made. | F14: VERIFIED: official Learn SE page retrieved; no retirement or release-date assertion used. | H14: 2025-06-16 — Displayed last-updated date
A19: Access audit date: 16 October 2026. A verified GitHub sample supports only the stated API/documentation claim. It is not a live API test, a product-price verification or evidence of vendor churn/CAC.

Sheet Checks
A1: Validation | Formula identities and scenario checks
A3: Check | B3: Result | C3: Expected / rationale
A4: Baseline CAC, Exchange | B4: =IF(ABS(CAC_LTV!B7-7000)<0.000001,"PASS","FAIL") -> PASS | C4: USD 7,000
A5: Baseline CAC, Google | B5: =IF(ABS(CAC_LTV!C7-4000)<0.000001,"PASS","FAIL") -> PASS | C5: USD 4,000
A6: Linked churn, n=4 | B6: =IF(ABS(CAC_LTV!B14-0.18*EXP(-0.4))<0.000000001,"PASS","FAIL") -> PASS | C6: Unrounded baseline used throughout
A7: Finite-horizon baseline LTV | B7: =IF(ABS(CAC_LTV!B8-17398.8668944561)<0.00001,"PASS","FAIL") -> PASS | C7: End-year cash; start-year survival
A8: Scenario n=4 links to B1 | B8: =IF(ABS(Churn!D6-CAC_LTV!B8)<0.00001,"PASS","FAIL") -> PASS | C8: Same provider-normalized LTV
A9: Exchange 5-year TCO | B9: =IF(ABS(TCO!B12-281000)<0.00001,"PASS","FAIL") -> PASS | C9: USD 41,000 + 5 × USD 48,000
A10: Google 5-year TCO | B10: =IF(ABS(TCO!C12-164000)<0.00001,"PASS","FAIL") -> PASS | C10: USD 15,000 + 5 × USD 29,800
A11: Annual schedule reconciliation | B11: =IF(AND(ABS(SUM(TCO!B19:B23)-TCO!B12)<0.00001,ABS(SUM(TCO!C19:C23)-TCO!C12)<0.00001),"PASS","FAIL") -> PASS | C11: Five annual rows reconcile
A12: High-price / low-FTE reversal | B12: =IF(ABS(Sensitivity!E7+27000)<0.00001,"PASS","FAIL") -> PASS | C12: Google savings = −USD 27,000
A13: Churn and retention direction | B13: =IF(AND(Churn!B4>Churn!B8,Churn!C4<Churn!C8),"PASS","FAIL") -> PASS | C13: Illustrative monotonic model
A14: First-year contribution timing | B14: =IF(ABS(CAC_LTV!G18-5700/1.1)<0.00001,"PASS","FAIL") -> PASS | C14: No churn before year-1 contribution
A15: Alternative-timing identity | B15: =IF(ABS(CAC_LTV!B24-CAC_LTV!B8*(1-CAC_LTV!B14))<0.00001,"PASS","FAIL") -> PASS | C15: About USD 15,300
A16: All baseline assumptions unchanged | B16: =IF(AND(Inputs!$B$16=4,Inputs!$B$25=7,Inputs!$B$21=0.3,Inputs!$B$5=5),"PASS","CHANGED") -> PASS | C16: Baseline checkpoints intentionally flag edits
A20: Baseline checks compare against the report values and will flag legitimate input changes. They are reconciliation checks, not an empirical validation of the behavioural model or evidence that a real deployment meets requirements.
